[
  {
    "src": "/images/icons/flutter-original.svg"
  },
  {
    "src": "/images/icons/html5-original.svg"
  },
  {
    "src": "/images/icons/css3-original.svg"
  },
  {
    "src": "/images/icons/sass-original.svg"
  },
  {
    "src": "/images/icons/typescript-original.svg"
  },
  {
    "src": "/images/icons/react-original.svg"
  },
  {
    "src": "/images/icons/nextjs-original.svg"
  },
  {
    "src": "/images/icons/vuejs-original.svg"
  },
  {
    "src": "/images/icons/svelte-original.svg"
  },
  {
    "src": "/images/icons/jest-plain.svg"
  },
  {
    "src": "/images/icons/git-original.svg"
  },
  {
    "src": "/images/icons/github-original.svg"
  },
  {
    "src": "/images/icons/gitlab-original.svg"
  },
  {
    "src": "/images/icons/vscode-original.svg"
  },
  {
    "src": "/images/icons/figma-original.svg"
  },
  {
    "src": "/images/icons/chrome-original.svg"
  },
  {
    "src": "/images/icons/java-original.svg"
  },
  {
    "src": "/images/icons/python-original.svg"
  },
  {
    "src": "/images/icons/javascript-original.svg"
  },
  {
    "src": "/images/icons/typescript-original.svg"
  },
  {
    "src": "/images/icons/php-original.svg"
  },
  {
    "src": "/images/icons/ruby-original.svg"
  },
  {
    "src": "/images/icons/go-original.svg"
  },
  {
    "src": "/images/icons/csharp-original.svg"
  },
  {
    "src": "/images/icons/kotlin-original.svg"
  },
  {
    "src": "/images/icons/dart-original.svg"
  },
  {
    "src": "/images/icons/spring-original.svg"
  },
  {
    "src": "/images/icons/express-original.svg"
  },
  {
    "src": "/images/icons/django-plain.svg"
  },
  {
    "src": "/images/icons/fastapi-original.svg"
  },
  {
    "src": "/images/icons/flask-original.svg"
  },
  {
    "src": "/images/icons/phoenix-original.svg"
  },
  {
    "src": "/images/icons/ktor-original.svg"
  },
  {
    "src": "/images/icons/mysql-original.svg"
  },
  {
    "src": "/images/icons/postgresql-original.svg"
  },
  {
    "src": "/images/icons/mongodb-original.svg"
  },
  {
    "src": "/images/icons/firebase-plain.svg"
  },
  {
    "src": "/images/icons/oracle-original.svg"
  },
  {
    "src": "/images/icons/sqlite-original.svg"
  },
  {
    "src": "/images/icons/nestjs-original.svg"
  },
  {
    "src": "/images/icons/nestjs-original-wordmark.svg"
  },
  {
    "src": "/images/icons/nginx-original.svg"
  }
]
